ecs_exec/__init__.py
ecs_exec/__main__.py
ecs_exec/version.py
ecs_exec-0.0.4.dist-info/LICENSE
ecs_exec-0.0.4.dist-info/METADATA
ecs_exec-0.0.4.dist-info/WHEEL
ecs_exec-0.0.4.dist-info/entry_points.txt
ecs_exec-0.0.4.dist-info/top_level.txt
ecs_exec-0.0.4.dist-info/RECORD
