Metadata-Version: 2.1
Name: ecs-exec
Version: 0.0.4
Summary: Simple script to allow one to execute commands on AWS ECS Fargate once ECS exec has been correctly configured.
Home-page: https://github.com/RingierIMU/ecs-exec
Author: Ringier Tech
Author-email: tools@ringier.co.za
License: UNKNOWN
Platform: UNKNOWN
Classifier: Programming Language :: Python :: 3
Classifier: License :: OSI Approved :: Apache Software License
Classifier: Operating System :: OS Independent
Requires-Python: >=3
License-File: LICENSE
Requires-Dist: boto3
Requires-Dist: argparse
